pychrome/__init__.py
pychrome/browser.py
pychrome/cli.py
pychrome/exceptions.py
pychrome/tab.py
py3chrome-0.2.9.dist-info/LICENSE
py3chrome-0.2.9.dist-info/METADATA
py3chrome-0.2.9.dist-info/WHEEL
py3chrome-0.2.9.dist-info/entry_points.txt
py3chrome-0.2.9.dist-info/top_level.txt
py3chrome-0.2.9.dist-info/RECORD
