Metadata-Version: 2.1
Name: py3chrome
Version: 0.2.9
Summary: A Python Package for the Google Chrome Dev Protocol
Home-page: https://github.com/ostorlab/py3chrome
Author: fate0
Author-email: fate0@fatezero.org
License: BSD license
Keywords: pychrome
Classifier: Development Status :: 5 - Production/Stable
Classifier: Intended Audience :: Developers
Classifier: License :: OSI Approved :: BSD License
Classifier: Natural Language :: English
Classifier: Programming Language :: Python :: 3.10
Classifier: Topic :: Internet :: WWW/HTTP
Classifier: Topic :: Internet :: WWW/HTTP :: Browsers
License-File: LICENSE
Requires-Dist: click >=6.0
Requires-Dist: websocket-client >=0.44.0
Requires-Dist: requests >=2.13.0
